n8n_py/__init__.py
n8n_py/core.py
n8n_py/handler.py
n8n_py-0.0.6.dist-info/METADATA
n8n_py-0.0.6.dist-info/WHEEL
n8n_py-0.0.6.dist-info/top_level.txt
n8n_py-0.0.6.dist-info/RECORD
