Metadata-Version: 2.1
Name: n8n_py
Version: 0.0.6
Summary: Python SDK for n8n-nodes-python-function
Author-email: pyscripter99 <ryder@retzlaff.family>
Project-URL: Homepage, https://github.com/pyscripter99/n8n-py
Project-URL: Issues, http://github.com/pyscripter99/n8n-py/issues
Classifier: Programming Language :: Python :: 3
Requires-Python: >=3.8
Requires-Dist: flask
